zsmapping/__init__.py
zsmapping/zsclouds.py
zsmapping/zscustomer_maps.py
zsmapping-0.1.1.dist-info/METADATA
zsmapping-0.1.1.dist-info/WHEEL
zsmapping-0.1.1.dist-info/entry_points.txt
zsmapping-0.1.1.dist-info/top_level.txt
zsmapping-0.1.1.dist-info/RECORD
